assertive_mock_api_client/__init__.py
assertive_mock_api_client/client.py
assertive_mock_api_client/py.typed
assertive_mock_api_client-0.3.0.dist-info/licenses/LICENSE
assertive_mock_api_client-0.3.0.dist-info/METADATA
assertive_mock_api_client-0.3.0.dist-info/WHEEL
assertive_mock_api_client-0.3.0.dist-info/top_level.txt
assertive_mock_api_client-0.3.0.dist-info/RECORD
