Metadata-Version: 2.4
Name: assertive-mock-api-client
Version: 0.3.0
Summary: Api Client for Mock API Server
Requires-Python: >=3.10
License-File: LICENSE
Requires-Dist: assertive>=1.2.0
Requires-Dist: httpx>=0.28.1
Requires-Dist: pydantic>=2.11.3
Dynamic: license-file
